BioMetaDB/__init__.py
BioMetaDB/dbdm.py
BioMetaDB/Accessories/__init__.py
BioMetaDB/Accessories/arg_parse.pyx
BioMetaDB/Accessories/bio_ops.pyx
BioMetaDB/Accessories/get.py
BioMetaDB/Accessories/ops.pxd
BioMetaDB/Accessories/ops.pyx
BioMetaDB/Accessories/program_caller.pyx
BioMetaDB/Accessories/range_ops.py
BioMetaDB/Accessories/update_data.py
BioMetaDB/AccessoryScripts/__init__.py
BioMetaDB/AccessoryScripts/edit_fix_file.py
BioMetaDB/Config/__init__.py
BioMetaDB/Config/config_manager.py
BioMetaDB/Config/directory_manager.py
BioMetaDB/DBManagers/__init__.py
BioMetaDB/DBManagers/class_manager.pyx
BioMetaDB/DBManagers/integrity_manager.pxd
BioMetaDB/DBManagers/integrity_manager.pyx
BioMetaDB/DBManagers/type_mapper.py
BioMetaDB/DBManagers/update_manager.pyx
BioMetaDB/DBOperations/__init__.py
BioMetaDB/DBOperations/_dbdm.py
BioMetaDB/DBOperations/create_database.py
BioMetaDB/DBOperations/create_table_in_existing_database.py
BioMetaDB/DBOperations/delete_from_table.py
BioMetaDB/DBOperations/fix.py
BioMetaDB/DBOperations/integrity_check.py
BioMetaDB/DBOperations/move_project.py
BioMetaDB/DBOperations/remove_columns_from_table.py
BioMetaDB/DBOperations/remove_table_from_database.py
BioMetaDB/DBOperations/summarize_database.py
BioMetaDB/DBOperations/update_existing_table.py
BioMetaDB/DataStructures/__init__.py
BioMetaDB/DataStructures/record_list.pxd
BioMetaDB/DataStructures/record_list.pyx
BioMetaDB/Exceptions/__init__.py
BioMetaDB/Exceptions/config_manager_exceptions.py
BioMetaDB/Exceptions/create_database_exceptions.py
BioMetaDB/Exceptions/directory_exceptions.py
BioMetaDB/Exceptions/error.py
BioMetaDB/Exceptions/fix_exceptions.py
BioMetaDB/Exceptions/get_exceptions.py
BioMetaDB/Exceptions/record_list_exceptions.py
BioMetaDB/Exceptions/remove_columns_from_table_exceptions.py
BioMetaDB/Exceptions/summarize_database_exceptions.py
BioMetaDB/Indexers/__init__.py
BioMetaDB/Indexers/index_extensions.py
BioMetaDB/Indexers/index_mapper.py
BioMetaDB/Models/__init__.py
BioMetaDB-0.1.2.6.dist-info/entry_points.txt
BioMetaDB-0.1.2.6.dist-info/LICENSE.txt
BioMetaDB-0.1.2.6.dist-info/WHEEL
BioMetaDB-0.1.2.6.dist-info/METADATA
BioMetaDB-0.1.2.6.dist-info/RECORD
